exiftool_wrapper/__init__.py
exiftool_wrapper/version.py
exiftool_wrapper/wrapper.py
exiftool_wrapper-0.3.0.dist-info/METADATA
exiftool_wrapper-0.3.0.dist-info/WHEEL
exiftool_wrapper-0.3.0.dist-info/RECORD
