Metadata-Version: 2.4
Name: exiftool-wrapper
Version: 0.3.0
Summary: A lightweight wrapper for exiftool
Author-email: Nils Philippsen <nils@tiptoe.de>
License-Expression: LGPL-3.0-or-later
Requires-Python: <4,>=3.12.0
